aws_bedrock_runtime_mate/__init__.py
aws_bedrock_runtime_mate/_version.py
aws_bedrock_runtime_mate/api.py
aws_bedrock_runtime_mate/converse.py
aws_bedrock_runtime_mate/converse_stream.py
aws_bedrock_runtime_mate/paths.py
aws_bedrock_runtime_mate/patterns/__init__.py
aws_bedrock_runtime_mate/patterns/api.py
aws_bedrock_runtime_mate/patterns/multi_round_converse.py
aws_bedrock_runtime_mate/vendor/__init__.py
aws_bedrock_runtime_mate/vendor/pytest_cov_helper.py
aws_bedrock_runtime_mate-0.1.1.dist-info/AUTHORS.rst
aws_bedrock_runtime_mate-0.1.1.dist-info/LICENSE.txt
aws_bedrock_runtime_mate-0.1.1.dist-info/METADATA
aws_bedrock_runtime_mate-0.1.1.dist-info/WHEEL
aws_bedrock_runtime_mate-0.1.1.dist-info/RECORD
